aris_apps/myapp/__init__.py
aris_apps/myapp/app.py
aris_apps/myapp/utils.py
aris_apps/myapp/config/mpl_settings_envelope.json
aris_apps/myapp/config/mpl_settings_trajectory.json
aris_apps/myapp/ui/__init__.py
aris_apps/myapp/ui/resources_rc.py
aris_apps/myapp/ui/ui_app.py
aris_apps-2.0.0.dist-info/LICENSE
aris_apps-2.0.0.dist-info/METADATA
aris_apps-2.0.0.dist-info/WHEEL
aris_apps-2.0.0.dist-info/entry_points.txt
aris_apps-2.0.0.dist-info/top_level.txt
aris_apps-2.0.0.dist-info/RECORD
