Metadata-Version: 2.1
Name: aris-apps
Version: 2.0.0
Summary: Physics online simulator with FRIB built upon PHANTASY framework
Home-page: UNKNOWN
License: GPL-2+
Platform: UNKNOWN
